pas.plugins.ldap-1.8.4-py3.11-nspkg.pth
pas/plugins/ldap/__init__.py
pas/plugins/ldap/cache.py
pas/plugins/ldap/cache.rst
pas/plugins/ldap/cache_volatile.zcml
pas/plugins/ldap/configure.zcml
pas/plugins/ldap/defaults.py
pas/plugins/ldap/interfaces.py
pas/plugins/ldap/monkey.py
pas/plugins/ldap/plugin.py
pas/plugins/ldap/properties.py
pas/plugins/ldap/properties.rst
pas/plugins/ldap/properties.yaml
pas/plugins/ldap/setuphandlers.py
pas/plugins/ldap/sheet.py
pas/plugins/ldap/testing.py
pas/plugins/ldap/plonecontrolpanel/__init__.py
pas/plugins/ldap/plonecontrolpanel/cache.py
pas/plugins/ldap/plonecontrolpanel/configure.zcml
pas/plugins/ldap/plonecontrolpanel/controlpanel.pt
pas/plugins/ldap/plonecontrolpanel/controlpanel.py
pas/plugins/ldap/plonecontrolpanel/exportimport.py
pas/plugins/ldap/plonecontrolpanel/inspector.pt
pas/plugins/ldap/plonecontrolpanel/inspector.py
pas/plugins/ldap/plonecontrolpanel/setuphandlers.py
pas/plugins/ldap/plonecontrolpanel/upgrades.py
pas/plugins/ldap/plonecontrolpanel/profiles/base/componentregistry.xml
pas/plugins/ldap/plonecontrolpanel/profiles/base/ldapsettings.xml
pas/plugins/ldap/plonecontrolpanel/profiles/base/metadata.xml
pas/plugins/ldap/plonecontrolpanel/profiles/base/registry.xml
pas/plugins/ldap/plonecontrolpanel/profiles/plone5/controlpanel.xml
pas/plugins/ldap/plonecontrolpanel/profiles/plone5/metadata.xml
pas/plugins/ldap/plonecontrolpanel/profiles/plone5/registry.xml
pas/plugins/ldap/plonecontrolpanel/profiles/uninstall/controlpanel.xml
pas/plugins/ldap/plonecontrolpanel/profiles/uninstall/registry.xml
pas/plugins/ldap/profile/metadata.xml
pas/plugins/ldap/tests/__init__.py
pas/plugins/ldap/tests/test_doctests.py
pas/plugins/ldap/tests/test_plugin.py
pas/plugins/ldap/zmi/__init__.py
pas/plugins/ldap/zmi/add_plugin.pt
pas/plugins/ldap/zmi/configure.zcml
pas/plugins/ldap/zmi/ldap.png
pas/plugins/ldap/zmi/manage_plugin.pt
pas/plugins/ldap/zmi/manage_plugin.py
pas_plugins_ldap-1.8.4.dist-info/licenses/LICENSE.rst
pas_plugins_ldap-1.8.4.dist-info/METADATA
pas_plugins_ldap-1.8.4.dist-info/WHEEL
pas_plugins_ldap-1.8.4.dist-info/entry_points.txt
pas_plugins_ldap-1.8.4.dist-info/namespace_packages.txt
pas_plugins_ldap-1.8.4.dist-info/top_level.txt
pas_plugins_ldap-1.8.4.dist-info/RECORD
