Metadata-Version: 2.4
Name: pas.plugins.ldap
Version: 1.8.4
Summary: LDAP/AD Plugin for Plone/Zope PluggableAuthService (users+groups)
Home-page: https://github.com/collective/pas.plugins.ldap/
Author: BlueDynamics Alliance
Author-email: dev@bluedynamics.com
License: GPLv2
Keywords: zope pas plone ldap authentication plugin
Classifier: Development Status :: 5 - Production/Stable
Classifier: Environment :: Web Environment
Classifier: Framework :: Plone :: 5.1
Classifier: Framework :: Plone :: 5.2
Classifier: Framework :: Plone :: Addon
Classifier: Framework :: Plone
Classifier: Framework :: Zope :: 2
Classifier: Framework :: Zope :: 4
Classifier: Framework :: Zope
Classifier: License :: OSI Approved :: GNU General Public License v2 (GPLv2)
Classifier: Operating System :: OS Independent
Classifier: Programming Language :: Python :: 2.7
Classifier: Programming Language :: Python :: 3.6
Classifier: Programming Language :: Python :: 3.7
Classifier: Programming Language :: Python
Classifier: Topic :: System :: Systems Administration :: Authentication/Directory :: LDAP
License-File: LICENSE.rst
Requires-Dist: AccessControl>=3.0
Requires-Dist: Acquisition
Requires-Dist: bda.cache
Requires-Dist: node
Requires-Dist: node.ext.ldap>=1.1
Requires-Dist: odict
Requires-Dist: plone.registry
Requires-Dist: Products.CMFCore
Requires-Dist: Products.GenericSetup
Requires-Dist: Products.PlonePAS
Requires-Dist: Products.PluggableAuthService
Requires-Dist: Products.statusmessages
Requires-Dist: python-ldap>=3.2.0
Requires-Dist: setuptools
Requires-Dist: six
Requires-Dist: yafowil>=2.3.1
Requires-Dist: yafowil.plone>=5.0.0a1
Requires-Dist: yafowil.bootstrap>=2.0.0a1
Requires-Dist: yafowil.widget.array
Requires-Dist: yafowil.widget.dict
Requires-Dist: yafowil.yaml
Requires-Dist: zope.component
Requires-Dist: zope.globalrequest
Requires-Dist: zope.i18nmessageid
Requires-Dist: zope.interface
Requires-Dist: zope.traversing
Provides-Extra: test
Requires-Dist: plone.testing; extra == "test"
Requires-Dist: zope.configuration; extra == "test"
Provides-Extra: plone
Requires-Dist: Plone; extra == "plone"
Dynamic: author
Dynamic: author-email
Dynamic: classifier
Dynamic: description
Dynamic: home-page
Dynamic: keywords
Dynamic: license
Dynamic: license-file
Dynamic: provides-extra
Dynamic: requires-dist
Dynamic: summary
